surreal_mcp/__init__.py
surreal_mcp/__main__.py
surreal_mcp/server.py
surreal_mcp/database/__init__.py
surreal_mcp/database/connection_pool.py
surreal_mcp-0.2.0.dist-info/METADATA
surreal_mcp-0.2.0.dist-info/WHEEL
surreal_mcp-0.2.0.dist-info/entry_points.txt
surreal_mcp-0.2.0.dist-info/licenses/LICENSE
surreal_mcp-0.2.0.dist-info/RECORD
