Metadata-Version: 2.4
Name: surreal-mcp
Version: 0.2.0
Summary: MCP Server for SurrealDB - Bridge AI assistants with SurrealDB databases
Author-email: Luis Novo <lfnovo@gmail.com>
License-Expression: MIT
License-File: LICENSE
Requires-Python: >=3.10.6
Requires-Dist: fastmcp>=2.11.0
Requires-Dist: loguru>=0.7.0
Requires-Dist: surrealdb>=1.0.6
